facetrackr/__init__.py
facetrackr/config.py
facetrackr/face_collection.py
facetrackr/video_processing.py
facetrackr-0.2.dist-info/METADATA
facetrackr-0.2.dist-info/WHEEL
facetrackr-0.2.dist-info/entry_points.txt
facetrackr-0.2.dist-info/top_level.txt
facetrackr-0.2.dist-info/RECORD
