Metadata-Version: 2.2
Name: facetrackr
Version: 0.2
Requires-Dist: boto3
Requires-Dist: opencv-python
Requires-Dist: numpy
Dynamic: description
Dynamic: description-content-type
Dynamic: requires-dist
